d2lbook/__init__.py
d2lbook/_version.py
d2lbook/activate.py
d2lbook/build.py
d2lbook/clear.py
d2lbook/colab.py
d2lbook/common.py
d2lbook/config.py
d2lbook/config_default.ini
d2lbook/deploy.py
d2lbook/library.py
d2lbook/library_test.py
d2lbook/main.py
d2lbook/markdown.py
d2lbook/markdown_test.py
d2lbook/notebook.py
d2lbook/notebook_test.py
d2lbook/resource.py
d2lbook/resource_test.py
d2lbook/rst.py
d2lbook/rst_test.py
d2lbook/sagemaker.py
d2lbook/slides.py
d2lbook/slides_test.py
d2lbook/sphinx.py
d2lbook/sphinx_template.py
d2lbook/tab.py
d2lbook/translate.py
d2lbook/upload_doc_s3.sh
d2lbook/upload_github.sh
d2lbook/utils.py
d2lbook-1.0.3.dist-info/LICENSE
d2lbook-1.0.3.dist-info/METADATA
d2lbook-1.0.3.dist-info/WHEEL
d2lbook-1.0.3.dist-info/entry_points.txt
d2lbook-1.0.3.dist-info/top_level.txt
d2lbook-1.0.3.dist-info/RECORD
