Metadata-Version: 2.1
Name: d2lbook
Version: 1.0.3
Summary: Create an online book with Jupyter Notebooks and Sphinx
Home-page: https://book.d2l.ai
Author: D2L Developers
Author-email: d2l.devs@gmail.com
License: Apache-2.0
Platform: UNKNOWN
Requires-Python: >=3.8
License-File: LICENSE
Requires-Dist: jupyter
Requires-Dist: regex
Requires-Dist: sphinx (==5.3.0)
Requires-Dist: recommonmark
Requires-Dist: sphinxcontrib-bibtex (==2.4.2)
Requires-Dist: pybtex-apa-style
Requires-Dist: d2l-notedown
Requires-Dist: mxtheme (>=0.3.17)
Requires-Dist: sphinxcontrib-svg2pdfconverter
Requires-Dist: numpydoc
Requires-Dist: awscli
Requires-Dist: gitpython
Requires-Dist: sphinx-autodoc-typehints
Requires-Dist: astor
Requires-Dist: yapf
Requires-Dist: fasteners
Requires-Dist: isort
